wldetect/__init__.py
wldetect/_version.py
wldetect/api.py
wldetect/config.py
wldetect/softmax.py
wldetect/tokenization.py
wldetect/cli/__init__.py
wldetect/cli/main.py
wldetect/cli/utils.py
wldetect/cli/commands/__init__.py
wldetect/cli/commands/create_lookup.py
wldetect/cli/commands/detect.py
wldetect/cli/commands/eval.py
wldetect/cli/commands/train.py
wldetect/models/lookup_table_exp.safetensors
wldetect/models/model_config.yaml
wldetect/training/__init__.py
wldetect/training/class_weights.py
wldetect/training/datasets.py
wldetect/training/embeddings.py
wldetect/training/flores_eval.py
wldetect/training/lookup_table.py
wldetect/training/losses.py
wldetect/training/model.py
wldetect/training/trainer.py
wldetect-0.1.2.dist-info/METADATA
wldetect-0.1.2.dist-info/WHEEL
wldetect-0.1.2.dist-info/entry_points.txt
wldetect-0.1.2.dist-info/licenses/LICENSE
wldetect-0.1.2.dist-info/RECORD
