Metadata-Version: 2.4
Name: wldetect
Version: 0.1.2
Summary: Fast, accurate language detection using static LLM embeddings
Project-URL: Homepage, https://github.com/dleemiller/WordLlamaDetect
Project-URL: Documentation, https://github.com/dleemiller/WordLlamaDetect/tree/main/docs
Project-URL: Repository, https://github.com/dleemiller/WordLlamaDetect
Project-URL: Bug Tracker, https://github.com/dleemiller/WordLlamaDetect/issues
Author-email: Lee Miller <dleemiller@gmail.com>
License: Apache-2.0
License-File: LICENSE
Keywords: embeddings,gemma,language-detection,llm,machine-learning,nlp
Classifier: Development Status :: 4 - Beta
Classifier: Intended Audience :: Developers
Classifier: Intended Audience :: Science/Research
Classifier: License :: OSI Approved :: Apache Software License
Classifier: Operating System :: OS Independent
Classifier: Programming Language :: Python :: 3
Classifier: Programming Language :: Python :: 3.12
Classifier: Programming Language :: Python :: 3.13
Classifier: Topic :: Scientific/Engineering :: Artificial Intelligence
Classifier: Topic :: Text Processing :: Linguistic
Requires-Python: >=3.12
Requires-Dist: numpy>=2.3.5
Requires-Dist: pydantic>=2.12.4
Requires-Dist: pyyaml>=6.0.2
Requires-Dist: safetensors>=0.4.5
Requires-Dist: tokenizers>=0.22.0
Provides-Extra: cu128
Requires-Dist: datasets>=4.0.0; extra == 'cu128'
Requires-Dist: huggingface-hub>=0.34.4; extra == 'cu128'
Requires-Dist: matplotlib>=3.10.7; extra == 'cu128'
Requires-Dist: rich>=14.2.0; extra == 'cu128'
Requires-Dist: scikit-learn>=1.7.1; extra == 'cu128'
Requires-Dist: seaborn>=0.13.2; extra == 'cu128'
Requires-Dist: tensorboard>=2.20.0; extra == 'cu128'
Requires-Dist: torch>=2.8.0; extra == 'cu128'
Requires-Dist: torchvision>=0.23.0; extra == 'cu128'
Requires-Dist: tqdm>=4.66.4; extra == 'cu128'
Requires-Dist: transformers>=4.57.1; extra == 'cu128'
Provides-Extra: dev
Requires-Dist: pre-commit>=4.5.0; extra == 'dev'
Requires-Dist: pytest-cov>=6.0.0; extra == 'dev'
Requires-Dist: pytest-mock>=3.15.0; extra == 'dev'
Requires-Dist: pytest>=8.3.3; extra == 'dev'
Requires-Dist: ruff>=0.14.7; extra == 'dev'
Provides-Extra: training
Requires-Dist: datasets>=4.0.0; extra == 'training'
Requires-Dist: huggingface-hub>=0.34.4; extra == 'training'
Requires-Dist: matplotlib>=3.10.7; extra == 'training'
Requires-Dist: rich>=14.2.0; extra == 'training'
Requires-Dist: scikit-learn>=1.7.1; extra == 'training'
Requires-Dist: seaborn>=0.13.2; extra == 'training'
Requires-Dist: tensorboard>=2.20.0; extra == 'training'
Requires-Dist: torch>=2.8.0; extra == 'training'
Requires-Dist: tqdm>=4.66.4; extra == 'training'
Requires-Dist: transformers>=4.57.1; extra == 'training'
